{"appid":1245620,"name":"ELDEN RING","developer":"FromSoftware, Inc.","publisher":"FromSoftware, Inc., Bandai Namco Entertainment","score_rank":"","positive":966025,"negative":74313,"userscore":0,"owners":"20,000,000 .. 50,000,000","average_forever":8048,"average_2weeks":683,"median_forever":5406,"median_2weeks":343,"price":"5999","initialprice":"5999","discount":"0","ccu":49858,"languages":"English, French, Italian, German, Spanish - Spain, Japanese, Korean, Polish, Portuguese - Brazil, Russian, Simplified Chinese, Spanish - Latin America, Thai, Traditional Chinese, Arabic","genre":"Action, RPG","tags":{"Souls-like":6892,"Open World":4989,"Dark Fantasy":4902,"RPG":4653,"Difficult":4536,"Action RPG":3537,"Third Person":3377,"Multiplayer":3348,"Fantasy":3196,"Singleplayer":3086,"Online Co-Op":2990,"Action":2811,"Co-op":2422,"Atmospheric":2367,"PvP":2341,"Great Soundtrack":2325,"Violent":2258,"3D":2049,"Character Customization":1319,"Family Friendly":1306}}